<annotation>
    <folder>clean_data</folder>
    <filename>000420_jpg.rf.87751b740c1de31357f7a4dabdb699d9.jpg</filename>
    <size>
        <width>500</width>
        <height>334</height>
        <depth>3</depth>
    </size>
    <object>
        <name>Hard Hat</name>
        <difficult>0</difficult>
        <bndbox>
            <xmin>17</xmin>
            <ymin>186</ymin>
            <xmax>61</xmax>
            <ymax>229</ymax>
        </bndbox>
    </object>
    <object>
        <name>Person</name>
        <difficult>0</difficult>
        <bndbox>
            <xmin>1</xmin>
            <ymin>190</ymin>
            <xmax>88</xmax>
            <ymax>331</ymax>
        </bndbox>
    </object>
    <object>
        <name>Person</name>
        <difficult>0</difficult>
        <bndbox>
            <xmin>410</xmin>
            <ymin>193</ymin>
            <xmax>439</xmax>
            <ymax>287</ymax>
        </bndbox>
    </object>
</annotation>