<annotation>
    <folder>clean_data</folder>
    <filename>000848_jpg.rf.7ff850bb207bb3a94badc03b32775d79.jpg</filename>
    <size>
        <width>500</width>
        <height>375</height>
        <depth>3</depth>
    </size>
    <object>
        <name>Hard Hat</name>
        <difficult>0</difficult>
        <bndbox>
            <xmin>190</xmin>
            <ymin>130</ymin>
            <xmax>226</xmax>
            <ymax>172</ymax>
        </bndbox>
    </object>
    <object>
        <name>Hard Hat</name>
        <difficult>0</difficult>
        <bndbox>
            <xmin>114</xmin>
            <ymin>105</ymin>
            <xmax>168</xmax>
            <ymax>176</ymax>
        </bndbox>
    </object>
    <object>
        <name>Hard Hat</name>
        <difficult>0</difficult>
        <bndbox>
            <xmin>224</xmin>
            <ymin>138</ymin>
            <xmax>248</xmax>
            <ymax>174</ymax>
        </bndbox>
    </object>
    <object>
        <name>Hard Hat</name>
        <difficult>0</difficult>
        <bndbox>
            <xmin>252</xmin>
            <ymin>146</ymin>
            <xmax>277</xmax>
            <ymax>183</ymax>
        </bndbox>
    </object>
    <object>
        <name>Person</name>
        <difficult>0</difficult>
        <bndbox>
            <xmin>173</xmin>
            <ymin>133</ymin>
            <xmax>230</xmax>
            <ymax>365</ymax>
        </bndbox>
    </object>
    <object>
        <name>Person</name>
        <difficult>0</difficult>
        <bndbox>
            <xmin>220</xmin>
            <ymin>139</ymin>
            <xmax>254</xmax>
            <ymax>342</ymax>
        </bndbox>
    </object>
    <object>
        <name>Person</name>
        <difficult>0</difficult>
        <bndbox>
            <xmin>90</xmin>
            <ymin>106</ymin>
            <xmax>171</xmax>
            <ymax>372</ymax>
        </bndbox>
    </object>
    <object>
        <name>Person</name>
        <difficult>0</difficult>
        <bndbox>
            <xmin>251</xmin>
            <ymin>143</ymin>
            <xmax>290</xmax>
            <ymax>308</ymax>
        </bndbox>
    </object>
</annotation>