<annotation>
    <folder>clean_data</folder>
    <filename>001011_jpg.rf.8e7e19248d48d924298332caecf23deb.jpg</filename>
    <size>
        <width>607</width>
        <height>300</height>
        <depth>3</depth>
    </size>
    <object>
        <name>Person</name>
        <difficult>0</difficult>
        <bndbox>
            <xmin>35</xmin>
            <ymin>71</ymin>
            <xmax>103</xmax>
            <ymax>233</ymax>
        </bndbox>
    </object>
    <object>
        <name>Person</name>
        <difficult>0</difficult>
        <bndbox>
            <xmin>136</xmin>
            <ymin>68</ymin>
            <xmax>216</xmax>
            <ymax>246</ymax>
        </bndbox>
    </object>
    <object>
        <name>Person</name>
        <difficult>0</difficult>
        <bndbox>
            <xmin>195</xmin>
            <ymin>72</ymin>
            <xmax>221</xmax>
            <ymax>188</ymax>
        </bndbox>
    </object>
    <object>
        <name>Person</name>
        <difficult>0</difficult>
        <bndbox>
            <xmin>307</xmin>
            <ymin>75</ymin>
            <xmax>338</xmax>
            <ymax>183</ymax>
        </bndbox>
    </object>
    <object>
        <name>Person</name>
        <difficult>0</difficult>
        <bndbox>
            <xmin>374</xmin>
            <ymin>67</ymin>
            <xmax>429</xmax>
            <ymax>224</ymax>
        </bndbox>
    </object>
    <object>
        <name>Person</name>
        <difficult>0</difficult>
        <bndbox>
            <xmin>245</xmin>
            <ymin>62</ymin>
            <xmax>307</xmax>
            <ymax>240</ymax>
        </bndbox>
    </object>
    <object>
        <name>Person</name>
        <difficult>0</difficult>
        <bndbox>
            <xmin>416</xmin>
            <ymin>77</ymin>
            <xmax>442</xmax>
            <ymax>193</ymax>
        </bndbox>
    </object>
</annotation>