<annotation>
    <folder>clean_data</folder>
    <filename>001112_jpg.rf.2b1b5568f59f5165ec6e1a350078255e.jpg</filename>
    <size>
        <width>600</width>
        <height>400</height>
        <depth>3</depth>
    </size>
    <object>
        <name>Person</name>
        <difficult>0</difficult>
        <bndbox>
            <xmin>315</xmin>
            <ymin>69</ymin>
            <xmax>559</xmax>
            <ymax>397</ymax>
        </bndbox>
    </object>
    <object>
        <name>Vest</name>
        <difficult>0</difficult>
        <bndbox>
            <xmin>207</xmin>
            <ymin>118</ymin>
            <xmax>349</xmax>
            <ymax>373</ymax>
        </bndbox>
    </object>
    <object>
        <name>Hard Hat</name>
        <difficult>0</difficult>
        <bndbox>
            <xmin>386</xmin>
            <ymin>53</ymin>
            <xmax>487</xmax>
            <ymax>181</ymax>
        </bndbox>
    </object>
    <object>
        <name>Hard Hat</name>
        <difficult>0</difficult>
        <bndbox>
            <xmin>240</xmin>
            <ymin>79</ymin>
            <xmax>320</xmax>
            <ymax>180</ymax>
        </bndbox>
    </object>
    <object>
        <name>Vest</name>
        <difficult>0</difficult>
        <bndbox>
            <xmin>367</xmin>
            <ymin>119</ymin>
            <xmax>529</xmax>
            <ymax>389</ymax>
        </bndbox>
    </object>
    <object>
        <name>Person</name>
        <difficult>0</difficult>
        <bndbox>
            <xmin>199</xmin>
            <ymin>83</ymin>
            <xmax>361</xmax>
            <ymax>400</ymax>
        </bndbox>
    </object>
</annotation>