<annotation>
    <folder>Images</folder>
    <filename>image_from_china(1149).jpg</filename>
    <size>
        <width>911</width>
        <height>1216</height>
        <depth>3</depth>
    </size>
    <object>
        <name>Person</name>
        <difficult>0</difficult>
        <bndbox>
            <xmin>417</xmin>
            <ymin>377</ymin>
            <xmax>474</xmax>
            <ymax>514</ymax>
        </bndbox>
    </object>
    <object>
        <name>Hard Hat</name>
        <difficult>0</difficult>
        <bndbox>
            <xmin>425</xmin>
            <ymin>378</ymin>
            <xmax>453</xmax>
            <ymax>403</ymax>
        </bndbox>
    </object>
    <object>
        <name>Person</name>
        <difficult>0</difficult>
        <bndbox>
            <xmin>788</xmin>
            <ymin>1155</ymin>
            <xmax>846</xmax>
            <ymax>1216</ymax>
        </bndbox>
    </object>
    <object>
        <name>Hard Hat</name>
        <difficult>0</difficult>
        <bndbox>
            <xmin>797</xmin>
            <ymin>1155</ymin>
            <xmax>820</xmax>
            <ymax>1177</ymax>
        </bndbox>
    </object>
</annotation>