<annotation>
    <folder>Images</folder>
    <filename>image_from_china(3015).jpg</filename>
    <size>
        <width>911</width>
        <height>1216</height>
        <depth>3</depth>
    </size>
    <object>
        <name>Person</name>
        <difficult>0</difficult>
        <bndbox>
            <xmin>384</xmin>
            <ymin>421</ymin>
            <xmax>449</xmax>
            <ymax>613</ymax>
        </bndbox>
    </object>
    <object>
        <name>Person</name>
        <difficult>0</difficult>
        <bndbox>
            <xmin>444</xmin>
            <ymin>425</ymin>
            <xmax>482</xmax>
            <ymax>609</ymax>
        </bndbox>
    </object>
</annotation>