<annotation><folder>PPE_84</folder>
<filename>image_from_china(2846).jpg</filename>
<size>
<width>911</width>
<height>1216</height>
<depth>3</depth>
</size>
<object>
<name>Person</name>
<bndbox>

<xmin>141</xmin>
<ymin>566</ymin>
<xmax>436</xmax>
<ymax>1216</ymax>
</bndbox>
</object>
<object>
<name>Person</name>
<bndbox>

<xmin>369</xmin>
<ymin>436</ymin>
<xmax>584</xmax>
<ymax>1176</ymax>
</bndbox>
</object>
<object>
<name>Hard Hat</name>
<bndbox>

<xmin>168</xmin>
<ymin>566</ymin>
<xmax>299</xmax>
<ymax>684</ymax>
</bndbox>
</object>

</annotation>