<annotation>
    <folder>Images</folder>
    <filename>image_from_china(893).jpg</filename>
    <size>
        <width>911</width>
        <height>1216</height>
        <depth>3</depth>
    </size>
    <object>
        <name>Person</name>
        <difficult>0</difficult>
        <bndbox>
            <xmin>708</xmin>
            <ymin>491</ymin>
            <xmax>744</xmax>
            <ymax>572</ymax>
        </bndbox>
    </object>
    <object>
        <name>Hard Hat</name>
        <difficult>0</difficult>
        <bndbox>
            <xmin>722</xmin>
            <ymin>491</ymin>
            <xmax>734</xmax>
            <ymax>510</ymax>
        </bndbox>
    </object>
</annotation>