<annotation><folder>PPE_84</folder>
<filename>image_from_china(420).jpg</filename>
<size>
<width>911</width>
<height>1216</height>
<depth>3</depth>
</size>
<object>
<name>Person</name>
<bndbox>

<xmin>431</xmin>
<ymin>801</ymin>
<xmax>523</xmax>
<ymax>1000</ymax>
</bndbox>
</object>
<object>
<name>Person</name>
<bndbox>

<xmin>380</xmin>
<ymin>138</ymin>
<xmax>449</xmax>
<ymax>320</ymax>
</bndbox>
</object>
<object>
<name>Person</name>
<bndbox>

<xmin>270</xmin>
<ymin>168</ymin>
<xmax>331</xmax>
<ymax>310</ymax>
</bndbox>
</object>
<object>
<name>Person</name>
<bndbox>

<xmin>451</xmin>
<ymin>197</ymin>
<xmax>500</xmax>
<ymax>357</ymax>
</bndbox>
</object>
<object>
<name>Hard Hat</name>
<bndbox>

<xmin>399</xmin>
<ymin>138</ymin>
<xmax>426</xmax>
<ymax>155</ymax>
</bndbox>
</object>

</annotation>