<annotation><folder>PPE_84</folder>
<filename>image_from_china(1899).jpg</filename>
<size>
<width>911</width>
<height>1216</height>
<depth>3</depth>
</size>
<object>
<name>Person</name>
<bndbox>

<xmin>338</xmin>
<ymin>767</ymin>
<xmax>413</xmax>
<ymax>836</ymax>
</bndbox>
</object>
<object>
<name>Person</name>
<bndbox>

<xmin>425</xmin>
<ymin>724</ymin>
<xmax>495</xmax>
<ymax>816</ymax>
</bndbox>
</object>
<object>
<name>Hard Hat</name>
<bndbox>

<xmin>447</xmin>
<ymin>724</ymin>
<xmax>473</xmax>
<ymax>742</ymax>
</bndbox>
</object>

</annotation>